{
   "version": 35,
   "force":true,
   "entries":[
      {
         "id":"theme-2026-03-05",
         "title":"Theme Game",
         "subtitle":"Find the correct word that fits the hint",
         "challengeNumber":31,
         "availableOn":{
            "month":3,
            "day": 5,
         },
         "theme":{
            "name":"Movie Names",
            "icon":"lightbulb.max",
            "cardColor":"#4EC5FF"
         },
         "gamePreset":{
            "rounds":10,
            "timeLimit": 180,
            "numberOfHints": 10,
            "difficulty":"easy",
            "showIntro":false,
            "handHoldingMode":false,
            "maximumHandHoldingCounter":0
         },
         "rounds":[
  {
    "theme": "movies",
    "ageRange": "all",
    "hint": "A giant ship sinks after hitting an iceberg",
    "characters": ["T","I","T","A","N","I","C","L","S","R"],
    "correctWord": "TITANIC"
  },
  {
    "theme": "movies",
    "ageRange": "all",
    "hint": "A failed comedian becomes a criminal icon",
    "characters": ["J","O","K","E","R","L","S","T","A","N"],
    "correctWord": "JOKER"
  },
  {
    "theme": "movies",
    "ageRange": "all",
    "hint": "A thief enters dreams to plant an idea",
    "characters": ["I","N","C","E","P","T","I","O","N","L"],
    "correctWord": "INCEPTION"
  },
  {
    "theme": "movies",
    "ageRange": "all",
    "hint": "A Roman general fights in the arena",
    "characters": ["G","L","A","D","I","A","T","O","R","S"],
    "correctWord": "GLADIATOR"
  },
  {
    "theme": "movies",
    "ageRange": "all",
    "hint": "A deadly creature hunts a spaceship crew",
    "characters": ["A","L","I","E","N","L","S","T","R","A"],
    "correctWord": "ALIEN"
  },
  {
    "theme": "movies",
    "ageRange": "all",
    "hint": "A former assassin seeks revenge after losing his dog",
    "characters": ["J","O","H","N","W","I","C","K","L","S"],
    "correctWord": "JOHNWICK"
  },
  {
    "theme": "movies",
    "ageRange": "all",
    "hint": "A boxer rises from his father's shadow",
    "characters": ["C","R","E","E","D","L","S","T","A","R"],
    "correctWord": "CREED"
  },
  {
    "theme": "movies",
    "ageRange": "all",
    "hint": "A James Bond mission turns personal",
    "characters": ["S","K","Y","F","A","L","L","T","R","A"],
    "correctWord": "SKYFALL"
  },
  {
    "theme": "movies",
    "ageRange": "all",
    "hint": "A man with memory loss searches for the truth",
    "characters": ["M","E","M","E","N","T","O","L","S","A"],
    "correctWord": "MEMENTO"
  },
  {
    "theme": "movies",
    "ageRange": "all",
    "hint": "An underground club spirals out of control",
    "characters": ["F","I","G","H","T","C","L","U","B","S"],
    "correctWord": "FIGHTCLUB"
  }
]
      }
   ]
}
